guacamol/__init__.py
guacamol/assess_distribution_learning.py
guacamol/assess_goal_directed_generation.py
guacamol/benchmark_suites.py
guacamol/common_scoring_functions.py
guacamol/distribution_learning_benchmark.py
guacamol/distribution_matching_generator.py
guacamol/frechet_benchmark.py
guacamol/goal_directed_benchmark.py
guacamol/goal_directed_generator.py
guacamol/goal_directed_score_contributions.py
guacamol/py.typed
guacamol/score_modifier.py
guacamol/scoring_function.py
guacamol/standard_benchmarks.py
guacamol/data/__init__.py
guacamol/data/get_data.py
guacamol/data/holdout_set_gcm_v1.smiles
guacamol/utils/__init__.py
guacamol/utils/chemistry.py
guacamol/utils/data.py
guacamol/utils/descriptors.py
guacamol/utils/fingerprints.py
guacamol/utils/helpers.py
guacamol/utils/math.py
guacamol/utils/sampling_helpers.py
guacamol-0.5.5.dist-info/LICENSE
guacamol-0.5.5.dist-info/METADATA
guacamol-0.5.5.dist-info/WHEEL
guacamol-0.5.5.dist-info/top_level.txt
guacamol-0.5.5.dist-info/RECORD
