Metadata-Version: 2.1
Name: guacamol
Version: 0.5.5
Summary: Guacamol: benchmarks for de novo molecular design
Home-page: https://github.com/BenevolentAI/guacamol
Author: BenevolentAI
Author-email: guacamol@benevolent.ai
License: MIT
Requires-Python: >=3.6
Provides-Extra: rdkit
License-File: LICENSE
